borzoi_pytorch/__init__.py
borzoi_pytorch/config_borzoi.py
borzoi_pytorch/gene_utils.py
borzoi_pytorch/pytorch_borzoi_helpers.py
borzoi_pytorch/pytorch_borzoi_model.py
borzoi_pytorch/pytorch_borzoi_transformer.py
borzoi_pytorch/pytorch_borzoi_utils.py
borzoi_pytorch/precomputed/targets.txt
borzoi_pytorch-0.4.4.dist-info/LICENSE
borzoi_pytorch-0.4.4.dist-info/METADATA
borzoi_pytorch-0.4.4.dist-info/WHEEL
borzoi_pytorch-0.4.4.dist-info/top_level.txt
borzoi_pytorch-0.4.4.dist-info/RECORD
